setup.py
test_distro/Binomialdistribution.py
test_distro/Gaussiandistribution.py
test_distro/Generaldistribution.py
test_distro/__init__.py
test_distro.egg-info/PKG-INFO
test_distro.egg-info/SOURCES.txt
test_distro.egg-info/dependency_links.txt
test_distro.egg-info/not-zip-safe
test_distro.egg-info/top_level.txt